{
  "namespace": "crafting",

  "heartsrender": {
    "type": "panel",
    "anchor_from": "bottom_middle",
    "anchor_to": "bottom_middle",
    "size": [ 180, 50 ],
    "controls": [
      {
        "heart_rend@hud.heart_renderer": {
          "offset": [ -1, -10 ],
          "anchor_from": "bottom_left",
          "anchor_to": "bottom_left"
        }
      },
      {
        "horse_heart_rend_1@hud.horse_heart_renderer": {
          "offset": [ 180, -20 ],
          "anchor_from": "bottom_left",
          "anchor_to": "bottom_left",
          "bindings": [
            {
              "binding_name": "#show_survival_ui",
              "binding_name_override": "#visible"
            }
          ]
        }
      },
      {
        "armor_rend@hud.armor_renderer": {
          "offset": [ -1, -10 ],
          "anchor_from": "bottom_left",
          "anchor_to": "bottom_left"
        }
      },
      {
        "hunger_rend@hud.hunger_renderer": {
          "offset": [ 180, -10 ],
          "anchor_from": "bottom_left",
          "anchor_to": "bottom_left"
        }
      },
      {
        "bubbles_rend_0@hud.bubbles_renderer": {
          "offset": [ 180, -20 ],
          "anchor_from": "bottom_left",
          "anchor_to": "bottom_left",
          "bindings": [
            {
              "binding_name": "#is_not_riding",
              "binding_name_override": "#visible"
            }
          ]
        }
      }
    ],
    "bindings": [
      {
        "binding_name": "#show_survival_ui",
        "binding_name_override": "#visible"
      }
    ]
  },

  "inventory_x_gamepad_helper@common.gamepad_helper_x_14": {
    "bindings": [
      {
        "binding_name": "#gamepad_helper_x_visible",
        "binding_name_override": "#visible",
        "binding_condition": "always"
      }
    ]
  },

  "inventory_y_gamepad_helper@common.gamepad_helper_y_14": {
    "bindings": [
      {
        "binding_name": "#gamepad_helper_y_visible",
        "binding_name_override": "#visible",
        "binding_condition": "always"
      }
    ]
  },

  "inventory_a_gamepad_helper@common.gamepad_helper_a_14": {
    "bindings": [
      {
        "binding_name": "#gamepad_helper_a_visible",
        "binding_name_override": "#visible",
        "binding_condition": "always"
      }
    ]
  },

  "inventory_b_gamepad_helper@common.gamepad_helper_b_14": {},

  "gamepad_helper_bumpers": {
    "type": "panel",
    "anchor_from": "top_middle",
    "anchor_to": "bottom_middle",
    "size": [ "100%", 16 ],
    "$left_bumper_anchor_from|default": "top_left",
    "$left_bumper_anchor_to|default": "top_right",
    "$right_bumper_anchor_from|default": "top_right",
    "$right_bumper_anchor_to|default": "top_left",
    "controls": [
      {
        "gamepad_helper_left_bumper@common.gamepad_helper_left_bumper": {
          "offset": [ -1, 0 ],
          "anchor_from": "$left_bumper_anchor_from",
          "anchor_to": "$left_bumper_anchor_to",
          "$hide_description": true
        }
      },
      {
        "gamepad_helper_right_bumper@common.gamepad_helper_right_bumper": {
          "anchor_from": "$right_bumper_anchor_from",
          "anchor_to": "$right_bumper_anchor_to",
          "$hide_description": true
        }
      }
    ]
  },

  "gamepad_helper_left_trigger@common.gamepad_helper_left_trigger": {
    "$hide_description": true
  },

  "gamepad_helper_right_trigger@common.gamepad_helper_right_trigger": {
    "$hide_description": true
  },

  "container_gamepad_helpers_second_row": {
    "type": "stack_panel",
    "size": [ "100%", 18 ],
    "orientation": "horizontal",
    "controls": [
      { "buffer_panel_left": { "type": "panel", "size": [ 10, 0 ] } },
      {
        "left_thumbstick_visibility": {
          "type": "panel",
          "size": [ "100%c", "350%" ],
          "controls": [
            {
              "gamepad_helper_thumbstick_left@common.gamepad_helper_thumbstick_left": {
                "bindings": [
                  {
                    "binding_name": "#gamepad_helper_ls_visible",
                    "binding_name_override": "#visible",
                    "binding_condition": "always"
                  }
                ]
              }
            }
          ]
        }
      },
      { "fill_panel": { "type": "panel", "size": [ "fill", 0 ] } },
      {
        "right_thumbstick_visibility": {
          "type": "panel",
          "size": [ "100%c", "100%" ],
          "controls": [
            {
              "gamepad_helper_thumbstick_right@common.gamepad_helper_thumbstick_right": {
                "bindings": [
                  {
                    "binding_name": "#gamepad_helper_rs_visible",
                    "binding_name_override": "#visible",
                    "binding_condition": "always"
                  }
                ]
              }
            }
          ]
        }
      },
      { "buffer_panel_right": { "type": "panel", "size": [ 10, 0 ] } }
    ]
  },

  "crafting_root_panel@common.root_panel": {
    "type": "input_panel",
    "button_mappings": [
      { "from_button_id": "button.menu_select", "to_button_id": "button.destroy_selection", "mapping_type": "pressed" },
      { "from_button_id": "button.menu_secondary_select", "to_button_id": "button.container_reset_held", "mapping_type": "pressed" },
      { "from_button_id": "button.menu_ok", "to_button_id": "button.destroy_selection", "mapping_type": "pressed" },
      { "from_button_id": "button.controller_back", "to_button_id": "button.destroy_selection", "mapping_type": "pressed", "ignored": "(not $is_ps4)" },
      { "from_button_id": "button.controller_select", "to_button_id": "button.clear_hotbar_or_remove_one", "mapping_type": "pressed" },
      { "from_button_id": "button.controller_secondary_select", "to_button_id": "button.container_reset_held", "mapping_type": "pressed" }
    ]
  },

  "drop_item_panel": {
    "type": "input_panel",
    "button_mappings": [
      { "from_button_id": "button.menu_select", "to_button_id": "button.cursor_drop_all", "mapping_type": "pressed" },
      { "from_button_id": "button.menu_secondary_select", "to_button_id": "button.cursor_drop_one", "mapping_type": "pressed" },
      { "from_button_id": "button.menu_ok", "to_button_id": "button.cursor_drop_all", "mapping_type": "pressed" },
      { "from_button_id": "button.controller_back", "to_button_id": "button.cursor_drop_all", "mapping_type": "pressed", "ignored": "(not $is_ps4)" },
      { "from_button_id": "button.controller_select", "to_button_id": "button.cursor_drop_one", "mapping_type": "pressed" },
      { "from_button_id": "button.controller_secondary_select", "to_button_id": "button.cursor_drop_all", "mapping_type": "pressed" }
    ]
  },

  "inventory_container_slot_button@common.container_slot_button_prototype": {
    "$button_take_half_place_one|default": "button.container_take_half_place_one",
    "$button_auto_place|default": "button.container_auto_place",
    "$button_take_all_place_all|default": "button.container_take_all_place_all",
    "$coalesce_button|default": "button.coalesce_stack",
    "button_mappings": [
      { "from_button_id": "button.menu_cancel", "to_button_id": "button.try_menu_exit", "mapping_type": "pressed" },
      { "from_button_id": "button.menu_select", "to_button_id": "$button_take_all_place_all", "mapping_type": "pressed" },
      { "from_button_id": "button.menu_ok", "to_button_id": "$button_take_all_place_all", "mapping_type": "pressed" },
      { "from_button_id": "button.menu_secondary_select", "to_button_id": "$button_take_half_place_one", "mapping_type": "pressed" },
      { "from_button_id": "button.menu_auto_place", "to_button_id": "$button_auto_place", "mapping_type": "pressed" },
      { "from_button_id": "button.menu_inventory_drop", "to_button_id": "button.drop_one", "mapping_type": "pressed" },
      { "from_button_id": "button.menu_inventory_drop_all", "to_button_id": "button.drop_all", "mapping_type": "pressed" },
      { "from_button_id": "button.menu_select", "to_button_id": "$coalesce_button", "mapping_type": "double_pressed" },
      { "to_button_id": "button.shape_drawing", "mapping_type": "pressed" },
      { "to_button_id": "button.container_slot_hovered", "mapping_type": "pressed" }
    ]
  },

  "creative_hotbar_container_slot_button@crafting.inventory_container_slot_button": {
    "$button_auto_place": "button.container_auto_destroy"
  },

  "no_coalesce_container_slot_button@crafting.inventory_container_slot_button": {
    "button_mappings": [
      { "from_button_id": "button.menu_cancel", "to_button_id": "button.try_menu_exit", "mapping_type": "pressed" },
      { "from_button_id": "button.menu_select", "to_button_id": "$button_take_all_place_all", "mapping_type": "pressed" },
      { "from_button_id": "button.menu_ok", "to_button_id": "$button_take_all_place_all", "mapping_type": "pressed" },
      { "from_button_id": "button.menu_secondary_select", "to_button_id": "$button_take_half_place_one", "mapping_type": "pressed" },
      { "from_button_id": "button.menu_auto_place", "to_button_id": "$button_auto_place", "mapping_type": "pressed" },
      { "from_button_id": "button.menu_inventory_drop", "to_button_id": "button.drop_one", "mapping_type": "pressed" },
      { "from_button_id": "button.menu_inventory_drop_all", "to_button_id": "button.drop_all", "mapping_type": "pressed" },
      { "to_button_id": "button.shape_drawing", "mapping_type": "pressed" },
      { "to_button_id": "button.container_slot_hovered", "mapping_type": "pressed" }
    ]
  },

  "creative_no_coalesce_container_slot_button@crafting.no_coalesce_container_slot_button": {
    "$button_take_all_place_all": "button.recipe_select",
    "$button_take_half_place_one": "button.recipe_secondary",
    "$button_auto_place": "button.recipe_tertiary"
  },

  "output_no_coalesce_container_slot_button@crafting.no_coalesce_container_slot_button": {
    "$button_take_all_place_all": "button.crafting_output_primary",
    "$button_take_half_place_one": "button.crafting_output_secondary",
    "$button_auto_place": "button.crafting_output_tertiary"
  },

  "tab_image": { "type": "image", "layer": 2, "size": [ 24, 25 ] },
  "item_renderer": { "type": "custom", "renderer": "inventory_item_renderer", "size": [ 16, 16 ] },
  "inventory_icon": { "type": "image", "size": [ 19, 13 ], "texture": "textures/ui/inventory_icon" },
  "recipe_book_icon": { "type": "image", "size": [ 19, 13 ], "texture": "textures/ui/recipe_book_icon" },
  "creative_icon": { "type": "image", "size": [ 19, 13 ], "texture": "textures/ui/creative_icon" },
  "icon_image": { "layer": -1, "type": "image", "size": [ 17, 17 ] },
  "tab_front@crafting.tab_image": { "texture": "textures/ui/TabTopFront" },
  "tab_back@crafting.tab_image": { "texture": "textures/ui/TabTopBack" },
  "equipment_icon@crafting.icon_image": { "texture": "textures/ui/icon_recipe_equipment" },
  "construction_icon@crafting.icon_image": { "texture": "textures/ui/icon_recipe_construction" },
  "nature_icon@crafting.icon_image": { "texture": "textures/ui/icon_recipe_nature" },
  "search_icon@crafting.icon_image": { "texture": "textures/ui/magnifyingGlass" },
  "miscellaneous_icon@crafting.icon_image": { "texture": "textures/ui/icon_recipe_item" },

  "empty_tab_panel": {
    "type": "panel",
    "size": [ 24, 25 ],
    "controls": [ { "img@$tab_icon": {} } ]
  },

  "tab_wait_anim": { "anim_type": "wait", "duration": 0.8, "next": "@crafting.tab_offset_anim" },
  "tab_offset_anim": {
    "$top_tab_anim_start|default": [ 0, 27 ],
    "$top_tab_anim_end|default": [ 0, 0 ],
    "anim_type": "offset",
    "easing": "out_cubic",
    "from": "$top_tab_anim_start",
    "to": "$top_tab_anim_end",
    "duration": 0.5
  },

  "top_tab@common_tabs.tab_top": {
    "alpha": 0.2,
    "$anims|default": [],
    "anims": "$anims",
    "$offset|default": [ 0, 0 ],
    "offset": "$offset",
    "$toggle_focus_enabled": false,
    "$toggle_name": "navigation_tab",
    "$toggle_group_default_selected": "$construction_index",
    "$tab_content": "crafting.empty_tab_panel",
    "$allow_controller_back_button_mapping": "$is_ps4"
  },

  "search_tab@crafting.top_tab": {
    "$tab_view_binding_name": "search_tab_toggle",
    "$tab_icon": "crafting.search_icon",
    "$toggle_group_forced_index": "$search_index",
    "$toggle_binding_type": "global",
    "$toggle_state_binding_name": "#is_left_tab_search",
    "$top_tab_tts_name": "craftingScreen.tab.search",
    "$focus_id": "search_tab",
    "$focus_override_left": "nature_tab",
    "$focus_override_up": "FOCUS_OVERRIDE_STOP",
    "$unchecked_default_image": "textures/ui/button_borderless_lightpressednohover",
    "$unchecked_hover_image": "textures/ui/button_borderless_lightpressed",
    "$checked_default_image": "textures/ui/button_borderless_light"
  },

  "construction_tab@crafting.top_tab": {
    "$is_left_most_tab": true,
    "$tab_view_binding_name": "construction_tab_toggle",
    "$tab_icon": "crafting.construction_icon",
    "$toggle_group_forced_index": "$construction_index",
    "$toggle_binding_type": "global",
    "$toggle_state_binding_name": "#is_left_tab_construct",
    "$top_tab_tts_name": "craftingScreen.tab.construction",
    "$focus_id": "construction_tab",
    "$focus_override_right": "equipment_tab",
    "$unchecked_default_image": "textures/ui/button_borderless_lightpressednohover",
    "$checked_default_image": "textures/ui/button_borderless_light"
  },

  "equipment_tab@crafting.top_tab": {
    "$tab_view_binding_name": "equipment_tab_toggle",
    "$tab_icon": "crafting.equipment_icon",
    "$toggle_group_forced_index": "$equipment_index",
    "$toggle_binding_type": "global",
    "$toggle_state_binding_name": "#is_left_tab_equipment",
    "$top_tab_tts_name": "craftingScreen.tab.equipment",
    "$focus_id": "equipment_tab",
    "$focus_override_left": "construction_tab",
    "$focus_override_right": "items_tab",
    "$unchecked_default_image": "textures/ui/button_borderless_lightpressednohover",
    "$checked_default_image": "textures/ui/button_borderless_light"
  },

  "nature_tab@crafting.top_tab": {
    "$tab_view_binding_name": "nature_tab_toggle",
    "$tab_icon": "crafting.nature_icon",
    "$toggle_group_forced_index": "$nature_index",
    "$toggle_binding_type": "global",
    "$toggle_state_binding_name": "#is_left_tab_nature",
    "$top_tab_tts_name": "craftingScreen.tab.nature",
    "$focus_id": "nature_tab",
    "$focus_override_left": "items_tab",
    "$focus_override_right": "search_tab",
    "$unchecked_default_image": "textures/ui/button_borderless_lightpressednohover",
    "$checked_default_image": "textures/ui/button_borderless_light"
  },

  "items_tab@crafting.top_tab": {
    "$tab_view_binding_name": "items_tab_toggle",
    "$tab_icon": "crafting.miscellaneous_icon",
    "$toggle_group_forced_index": "$items_index",
    "$toggle_binding_type": "global",
    "$toggle_state_binding_name": "#is_left_tab_items",
    "$top_tab_tts_name": "craftingScreen.tab.items",
    "$focus_id": "items_tab",
    "$focus_override_left": "equipment_tab",
    "$focus_override_right": "nature_tab",
    "$unchecked_default_image": "textures/ui/button_borderless_lightpressednohover",
    "$checked_default_image": "textures/ui/button_borderless_light"
  },

  "tab_navigation_panel_layout": {
    "type": "stack_panel",
    "orientation": "horizontal",
    "size": [ "100%", 27 ],
    "ttsSectionContainer": true,
    "controls": [
      {
        "navigation_tabs": {
          "type": "panel",
          "size": [ "fill", "100%" ],
          "controls": [
            {
              "content": {
                "type": "stack_panel",
                "orientation": "vertical",
                "size": [ "100%", "100% + 4px" ],
                "offset": [ "-20%", "125%" ],
                "anchor_to": "top_left",
                "anchor_from": "top_left",
                "controls": [
                  {
                    "search_tab_holder": {
                      "type": "panel",
                      "size": [ 25, "100%" ],
                      "controls": [
                        { "search_tab_survival@crafting.search_tab": { "bindings": [ { "binding_type": "global", "binding_name": "(not #is_creative_mode)", "binding_name_override": "#visible" } ] } }
                      ]
                    }
                  }
                ]
              }
            }
          ]
        }
      }
    ]
  },

  "crafting_screen": {
    "$player_inventory_variant": "crafting.player_inventory"
  },

  "inventory_screen": {
    "$player_inventory_variant": "CrisXolt_anm_inventory_screen.player_inventory"
  },

  "recipe_inventory_screen_content/content_stack_panel": {
    "offset": [72, 0],
    "controls": [
      {
        "recipe_book_wrapper": {
          "type": "panel",
          "size":[0, "100%"],
          "controls":[
            {
              "recipe_book@crafting.recipe_book": {
                "anchor_from": "top_right",
                "anchor_to": "top_right",
                "size": [145, "100%"],
                "offset": [0, 0]
              }
            }
          ]
        }
      },
      {
        "center_fold@crafting.center_fold": {
          "size": [ 4, 166 ],
          "bindings": [
            {
              "binding_type": "global",
              "binding_name": "#is_recipe_book_layout",
              "binding_name_override": "#visible"
            }
          ]
        }
      },
      {
        "survival_padding": {
          "type": "panel",
          "size": [ 75, "100%" ],
          "bindings": [
            {
              "binding_type": "global",
              "binding_name": "#is_survival_layout",
              "binding_name_override": "#visible"
            }
          ]
        }
      },
      {
        "player_inventory@$player_inventory_variant": {
          "bindings": [
            {
              "binding_type": "global",
              "binding_name": "(not #is_creative_layout)",
              "binding_name_override": "#visible"
            }
          ]
        }
      },
      {
        "toolbar_anchor": {
          "type": "panel",
          "size": [ 0, "100%" ],
          "controls": [
            {
              "toolbar_panel@crafting.toolbar_panel": {
                "anchor_from": "top_right",
                "anchor_to": "bottom_right"
              }
            }
          ]
        }
      }
    ]
  }
}